agentix/__init__.py
agentix/planner.py
agentix/py.typed
agentix/workflow.py
agentix/agents/__init__.py
agentix/agents/agent.py
agentix/agents/autonomous_agent.py
agentix/agents/prompt_builder.py
agentix/agents/multi_agent/__init__.py
agentix/agents/multi_agent/agent_router.py
agentix/agents/multi_agent/agent_team.py
agentix/agents/multi_agent/llm_convergence_checker.py
agentix/evaluators/__init__.py
agentix/evaluators/simple_evaluator.py
agentix/llms/__init__.py
agentix/llms/gemini_chat.py
agentix/llms/openai_chat.py
agentix/llms/openai_embeddings.py
agentix/llms/together_chat.py
agentix/llms/types.py
agentix/memory/__init__.py
agentix/memory/composite_memory.py
agentix/memory/long_term_memory.py
agentix/memory/memory.py
agentix/memory/reflection_memory.py
agentix/memory/short_term_memory.py
agentix/memory/summarizing_memory.py
agentix/memory/vector_store.py
agentix/metrics/__init__.py
agentix/metrics/workflow_metrics.py
agentix/tools/__init__.py
agentix/tools/duckduckgo_tools.py
agentix/tools/firecrawl_tools.py
agentix/tools/function_tools.py
agentix/tools/tavily_tools.py
agentix/tools/tool_analyzer.py
agentix/tools/tool_error.py
agentix/tools/tool_metadata.py
agentix/tools/tool_request.py
agentix/tools/tools.py
agentix/tools/yfinance_tools.py
agentix/utils/__init__.py
agentix/utils/debug_logger.py
agentix_lib-0.4.0.dist-info/licenses/LICENSE
agentix_lib-0.4.0.dist-info/METADATA
agentix_lib-0.4.0.dist-info/WHEEL
agentix_lib-0.4.0.dist-info/top_level.txt
agentix_lib-0.4.0.dist-info/RECORD
