Metadata-Version: 2.4
Name: agentix-lib
Version: 0.4.0
Summary: A simple and modular agent framework with a focus on modularity and ease of use
Author-email: Gabriel Tomberlin <gabrieltomberlin14@gmail.com>
License: MIT License
Project-URL: Homepage, https://github.com/gabriel0110/agentix
Project-URL: Repository, https://github.com/gabriel0110/agentix
Project-URL: Documentation, https://github.com/gabriel0110/agentix#readme
Project-URL: Bug Tracker, https://github.com/gabriel0110/agentix/issues
Keywords: ai,agents,llm,automation,agentic
Classifier: Programming Language :: Python :: 3
Classifier: License :: OSI Approved :: MIT License
Classifier: Operating System :: OS Independent
Classifier: Development Status :: 4 - Beta
Classifier: Intended Audience :: Developers
Classifier: Topic :: Software Development :: Libraries :: Python Modules
Classifier: Topic :: Scientific/Engineering :: Artificial Intelligence
Requires-Python: >=3.9
License-File: LICENSE
Requires-Dist: openai>=1.65.0
Requires-Dist: pydantic>=2.0.0
Requires-Dist: aiohttp>=3.8.0
Requires-Dist: numpy>=1.20.0
Requires-Dist: python-dotenv>=1.0.0
Dynamic: license-file
